README.rst
setup.py
Epidaurus.egg-info/PKG-INFO
Epidaurus.egg-info/SOURCES.txt
Epidaurus.egg-info/dependency_links.txt
Epidaurus.egg-info/entry_points.txt
Epidaurus.egg-info/requires.txt
Epidaurus.egg-info/top_level.txt
epidaurus/__init__.py
epidaurus/controller.py
epidaurus/pid.py
epidaurus/schema.py
tests_manual/__init__.py
tests_manual/test_controller_model.py
tests_manual/test_controller_model_nomqtt.py
tests_manual/test_pid_csv.py
tests_manual/test_pid_model.py
tests_manual/test_pid_simple.py
tests_manual/test_trivial_flat.py
tests_unit/__init__.py
tests_unit/test_validateconfig.py
tools/__init__.py
tools/extract_trainingsdata.py
tools/model_trivial_flat.py