Metadata-Version: 1.2
Name: Epidaurus
Version: 0.1.6
Summary: PID based room temperature controller - to be used in combination with pelops/copreus, pelops/argaeus and pelops/alcathous.
Home-page: https://gitlab.com/pelops/epidaurus/
Author: Tobias Gawron-Deutsch
Author-email: tobias@strix.at
License: MIT license
Keywords: mqtt device driver rpi raspberry pi
Platform: UNKNOWN
Classifier: Development Status :: 4 - Beta
Classifier: Environment :: Console
Classifier: Environment :: No Input/Output (Daemon)
Classifier: Intended Audience :: Developers
Classifier: Programming Language :: Python :: 3
Classifier: Topic :: Utilities
Classifier: Topic :: Home Automation
Classifier: License :: OSI Approved :: MIT License
Requires-Python: >=3.5
